fluffy_cli/__init__.py
fluffy_cli/main.py
fluffy-1.8.0.dist-info/METADATA
fluffy-1.8.0.dist-info/WHEEL
fluffy-1.8.0.dist-info/entry_points.txt
fluffy-1.8.0.dist-info/top_level.txt
fluffy-1.8.0.dist-info/RECORD
