Metadata-Version: 2.1
Name: fluffy
Version: 1.8.0
Summary: UNKNOWN
Home-page: UNKNOWN
Author: Chris Kuehl
Author-email: ckuehl@ckuehl.me
License: UNKNOWN
Platform: UNKNOWN
Classifier: Programming Language :: Python :: 3
Requires-Dist: requests
